{"cameraMode":{"drawMode":0,"name":"Shaded","section":"Shading Mode"},"sceneLighting":true,"audioPlay":false,"sceneViewState":{"m_AlwaysRefresh":false,"showFog":true,"showSkybox":true,"showFlares":true,"showImageEffects":true,"showParticleSystems":true,"showVisualEffectGraphs":true,"m_FxEnabled":true},"in2DMode":false,"pivot":{"x":-2.387676954269409,"y":-10.964998245239258,"z":-1.4769964218139649},"rotation":{"x":-0.4032270908355713,"y":0.5708489418029785,"z":-0.3797628879547119,"w":-0.6060875654220581},"size":12.34708309173584,"orthographic":false}